xalanih/__init__.py
xalanih/__main__.py
xalanih/core/__init__.py
xalanih/core/connectioninfo.py
xalanih/core/constants.py
xalanih/core/dbconnector.py
xalanih/core/dbconnectorfactory.py
xalanih/core/dbcreator.py
xalanih/core/dbupdator.py
xalanih/core/logger.py
xalanih/core/requesthandler.py
xalanih/core/requesthandlerfactory.py
xalanih/core/sqlfileexecutor.py
xalanih/core/xalanihexception.py
xalanih/core/mysql/__init__.py
xalanih/core/mysql/mysqlconnector.py
xalanih/core/mysql/mysqlrequesthandler.py
xalanih/test/__init__.py
xalanih/test/test_dbconnectorfactory.py
xalanih/test/test_dbcreator_mysql.py
xalanih/test/test_dbupdator_mysql.py
xalanih/test/test_requesthandlerfactory.py
xalanih/test/test_sqlfileexecutor.py
xalanih/utils/__init__.py
xalanih/utils/parameters.py
xalanih-1.0.0.dist-info/METADATA
xalanih-1.0.0.dist-info/RECORD
xalanih-1.0.0.dist-info/WHEEL
xalanih-1.0.0.dist-info/top_level.txt
