Metadata-Version: 2.1
Name: xalanih
Version: 1.0.0
Summary: Xalanih is a python script made to help you version your SQL database.
Home-page: https://github.com/nhereman/Xalanih
Author: Hereman Nicolas
Author-email: nicolas.hereman@gmail.com
License: UNKNOWN
Platform: UNKNOWN
Classifier: Programming Language :: Python :: 3
Classifier: License :: OSI Approved :: MIT License
Classifier: Operating System :: OS Independent
Requires-Dist: sqlparse (>=0.2.4)
Requires-Dist: mysqlclient (>=1.3.12)
